thepassiveinvestor/__init__.py
thepassiveinvestor/collect_data.py
thepassiveinvestor/config.py
thepassiveinvestor/create_report.py
thepassiveinvestor/utils.py
thepassiveinvestor-1.2.2.dist-info/LICENSE.txt
thepassiveinvestor-1.2.2.dist-info/METADATA
thepassiveinvestor-1.2.2.dist-info/WHEEL
thepassiveinvestor-1.2.2.dist-info/RECORD
