Metadata-Version: 2.1
Name: thepassiveinvestor
Version: 1.2.2
Summary: Passive Investing for the Average Joe.
Home-page: https://www.jeroenbouma.com/projects/thepassiveinvestor
License: MIT
Keywords: Passive,Investing,Financial,Analysis,Fundamental,Technical,Quantitative,Database,Equities,Currencies,Economics,ETFs,Funds,Indices,Moneymarkets,Commodities,Options
Author: Jeroen Bouma
Requires-Python: >=3.10,<3.13
Classifier: Development Status :: 5 - Production/Stable
Classifier: Intended Audience :: Financial and Insurance Industry
Classifier: License :: OSI Approved :: MIT License
Classifier: Operating System :: OS Independent
Classifier: Programming Language :: Python :: 3
Classifier: Programming Language :: Python :: 3.10
Classifier: Programming Language :: Python :: 3.11
Classifier: Programming Language :: Python :: 3.12
Classifier: Topic :: Office/Business :: Financial :: Investment
Requires-Dist: pandas[computation,excel,performance] (>=2.2,<3.0)
Requires-Dist: urllib3 (>=1,<2)
Requires-Dist: yahooquery (>=2,<3)
Project-URL: Repository, https://github.com/JerBouma/thepassiveinvestor
